[
  {
    "comparisonGroupId": "arroz-basmati-cacarola-500g",
    "label": "Arroz basmati Caçarola 500g",
    "categoryId": "mercearia",
    "rules": {
      "size": 500,
      "sizeUnit": "g",
      "packCount": 1
    },
    "active": true
  },
  {
    "comparisonGroupId": "leite-uht-meio-gordo-marca-propria-1l",
    "label": "Leite UHT meio-gordo marca própria 1L",
    "categoryId": "lacteos_ovos",
    "rules": {
      "size": 1,
      "sizeUnit": "L",
      "packCount": 1
    },
    "active": true
  },
  {
    "comparisonGroupId": "banana-1kg",
    "label": "Banana 1kg",
    "categoryId": "fruta_legumes",
    "rules": {
      "size": 1,
      "sizeUnit": "kg",
      "packCount": 1
    },
    "active": true
  },
  {
    "comparisonGroupId": "bolachas-maria-800g-4un",
    "label": "Bolachas Maria Continente 800g (4 un)",
    "categoryId": "snacks_doces",
    "rules": {
      "size": 800,
      "sizeUnit": "g",
      "packCount": 4
    },
    "active": true
  },
  {
    "comparisonGroupId": "ovos-ar-livre-classe-ml-12un",
    "label": "Ovos de ar livre classe M/L Continente (12 un)",
    "categoryId": "lacteos_ovos",
    "rules": {
      "size": 12,
      "sizeUnit": "un",
      "packCount": 12
    },
    "active": true
  },
  {
    "comparisonGroupId": "abrilhantador-maquina-loica-1l",
    "label": "Abrilhantador máquina loiça Continente 1L",
    "categoryId": "limpeza_casa",
    "rules": {
      "size": 1,
      "sizeUnit": "L",
      "packCount": 1
    },
    "active": true
  },
  {
    "comparisonGroupId": "arroz-carolino-caravela-continente-1kg",
    "label": "Arroz carolino Caravela Continente 1kg",
    "categoryId": "mercearia",
    "rules": {
      "size": 1,
      "sizeUnit": "kg",
      "packCount": 1
    },
    "active": true
  },
  {
    "comparisonGroupId": "capsulas-cafe-delta-q-int-10-100un",
    "label": "Cápsulas Delta Q Qalidus Int 10 (100 un)",
    "categoryId": "bebidas",
    "rules": {
      "size": 100,
      "sizeUnit": "un",
      "packCount": 100
    },
    "active": true
  },
  {
    "comparisonGroupId": "douradinhos-peixe-840g-30un",
    "label": "Douradinhos de peixe 840g (30 un)",
    "categoryId": "congelados",
    "rules": {
      "size": 840,
      "sizeUnit": "g",
      "packCount": 30
    },
    "active": true
  },
  {
    "comparisonGroupId": "peito-frango-vacuo-1kg",
    "label": "Peito de frango embalado 1kg",
    "categoryId": "talho",
    "rules": {
      "size": 1,
      "sizeUnit": "kg",
      "packCount": 1
    },
    "active": true
  },
  {
    "comparisonGroupId": "arroz-basmati-pingo-doce-1kg",
    "label": "Arroz basmati Pingo Doce 1kg",
    "categoryId": "mercearia",
    "rules": {
      "size": 1,
      "sizeUnit": "kg",
      "packCount": 1
    },
    "active": true
  },
  {
    "comparisonGroupId": "douradinhos-peixe-iglo-420g",
    "label": "Douradinhos de peixe Iglo 420g",
    "categoryId": "congelados",
    "rules": {
      "size": 420,
      "sizeUnit": "g",
      "packCount": 1
    },
    "active": true
  },
  {
    "comparisonGroupId": "arroz-agulha-cigala-1kg",
    "label": "Arroz agulha Cigala 1kg",
    "categoryId": "mercearia",
    "rules": {
      "size": 1,
      "sizeUnit": "kg",
      "packCount": 1
    },
    "active": true
  },
  {
    "comparisonGroupId": "arroz-carolino-bom-sucesso-1kg",
    "label": "Arroz carolino Bom Sucesso 1kg",
    "categoryId": "mercearia",
    "rules": {
      "size": 1,
      "sizeUnit": "kg",
      "packCount": 1
    },
    "active": true
  },
  {
    "comparisonGroupId": "capsulas-cafe-delta-q-qalidus-80un",
    "label": "Cápsulas Delta Q Qalidus 80 un",
    "categoryId": "bebidas",
    "rules": {
      "size": 80,
      "sizeUnit": "un",
      "packCount": 80
    },
    "active": true
  },
  {
    "comparisonGroupId": "lombos-bacalhau-congelados-pingo-doce-800g",
    "label": "Lombos de bacalhau congelados Pingo Doce 800g",
    "categoryId": "congelados",
    "rules": {
      "size": 800,
      "sizeUnit": "g",
      "packCount": 1
    },
    "active": true
  }
]
